cdk_fargate_runner/__init__.py
cdk_fargate_runner/py.typed
cdk_fargate_runner/_jsii/__init__.py
cdk_fargate_runner/_jsii/fargate-runner@1.0.7.jsii.tgz
fargate_runner-1.0.7.dist-info/LICENSE
fargate_runner-1.0.7.dist-info/METADATA
fargate_runner-1.0.7.dist-info/WHEEL
fargate_runner-1.0.7.dist-info/top_level.txt
fargate_runner-1.0.7.dist-info/RECORD
