Metadata-Version: 2.1
Name: fargate-runner
Version: 1.0.7
Summary: AWS CDK Construct that run a Fargate task. Stack will process only when Fargate task executed successfully and all containers exit with code 0, otherwise rollback
Home-page: https://github.com/fanhongy/fargate-runner.git
Author: Stan Fan<fanhongy@amazon.com>
License: Apache-2.0
Project-URL: Source, https://github.com/fanhongy/fargate-runner.git
Classifier: Intended Audience :: Developers
Classifier: Operating System :: OS Independent
Classifier: Programming Language :: JavaScript
Classifier: Programming Language :: Python :: 3 :: Only
Classifier: Programming Language :: Python :: 3.8
Classifier: Programming Language :: Python :: 3.9
Classifier: Programming Language :: Python :: 3.10
Classifier: Programming Language :: Python :: 3.11
Classifier: Typing :: Typed
Classifier: Development Status :: 4 - Beta
Classifier: License :: OSI Approved
Requires-Python: ~=3.8
License-File: LICENSE
Requires-Dist: aws-cdk-lib <3.0.0,>=2.109.0
Requires-Dist: constructs <11.0.0,>=10.0.5
Requires-Dist: jsii <2.0.0,>=1.93.0
Requires-Dist: publication >=0.0.3
Requires-Dist: typeguard ~=2.13.3
